h2o_helium/__init__.py
h2o_helium-0.8.2.dist-info/METADATA
h2o_helium-0.8.2.dist-info/WHEEL
h2o_helium-0.8.2.dist-info/top_level.txt
h2o_helium-0.8.2.dist-info/RECORD
