Metadata-Version: 2.1
Name: h2o-helium
Version: 0.8.2
Summary: Client library for H2O Helium
Author-email: Prithvi Prabhu <prithvi.prabhu@gmail.com>
Project-URL: Source, https://github.com/h2oai/helium
Project-URL: Issues, https://github.com/h2oai/helium/issues
Project-URL: Documentation, https://github.com/h2oai/helium/wiki
Keywords: information-retrieval,LLM,large-language-models,question-answering,search,semantic-search,analytical-search,lexical-search,document-search,natural-language-querying
Classifier: Development Status :: 4 - Beta
Classifier: Programming Language :: Python
Classifier: Programming Language :: Python :: 3.8
Classifier: Programming Language :: Python :: 3.9
Classifier: Programming Language :: Python :: 3.10
Classifier: Programming Language :: Python :: 3.11
Classifier: Programming Language :: Python :: Implementation :: CPython
Classifier: Programming Language :: Python :: Implementation :: PyPy
Requires-Python: >=3.8
Requires-Dist: pydantic[dotenv] ==1.10.12
Requires-Dist: requests ==2.31.0
Requires-Dist: websockets ==11.0.3
Requires-Dist: pytest-xdist ==3.3.1
